odoo10_addon_web_widget_x2many_2d_matrix-10.0.1.0.1-py2.7-nspkg.pth
odoo/addons/web_widget_x2many_2d_matrix/README.rst
odoo/addons/web_widget_x2many_2d_matrix/__init__.py
odoo/addons/web_widget_x2many_2d_matrix/__manifest__.py
odoo/addons/web_widget_x2many_2d_matrix/i18n/ar.po
odoo/addons/web_widget_x2many_2d_matrix/i18n/de.po
odoo/addons/web_widget_x2many_2d_matrix/i18n/es.po
odoo/addons/web_widget_x2many_2d_matrix/i18n/fi.po
odoo/addons/web_widget_x2many_2d_matrix/i18n/fr.po
odoo/addons/web_widget_x2many_2d_matrix/i18n/hr.po
odoo/addons/web_widget_x2many_2d_matrix/i18n/it.po
odoo/addons/web_widget_x2many_2d_matrix/i18n/pt_BR.po
odoo/addons/web_widget_x2many_2d_matrix/i18n/sl.po
odoo/addons/web_widget_x2many_2d_matrix/i18n/tr.po
odoo/addons/web_widget_x2many_2d_matrix/static/description/icon.png
odoo/addons/web_widget_x2many_2d_matrix/static/description/screenshot.png
odoo/addons/web_widget_x2many_2d_matrix/static/src/css/web_widget_x2many_2d_matrix.css
odoo/addons/web_widget_x2many_2d_matrix/static/src/js/web_widget_x2many_2d_matrix.js
odoo/addons/web_widget_x2many_2d_matrix/static/src/xml/web_widget_x2many_2d_matrix.xml
odoo/addons/web_widget_x2many_2d_matrix/views/templates.xml
odoo10_addon_web_widget_x2many_2d_matrix-10.0.1.0.1.dist-info/DESCRIPTION.rst
odoo10_addon_web_widget_x2many_2d_matrix-10.0.1.0.1.dist-info/METADATA
odoo10_addon_web_widget_x2many_2d_matrix-10.0.1.0.1.dist-info/RECORD
odoo10_addon_web_widget_x2many_2d_matrix-10.0.1.0.1.dist-info/WHEEL
odoo10_addon_web_widget_x2many_2d_matrix-10.0.1.0.1.dist-info/metadata.json
odoo10_addon_web_widget_x2many_2d_matrix-10.0.1.0.1.dist-info/namespace_packages.txt
odoo10_addon_web_widget_x2many_2d_matrix-10.0.1.0.1.dist-info/top_level.txt
